Workbook

Sheet GENERAL Instructions
A1: Identify the Type of Setup Requested by the NW Client

Sheet Property Setup Instructions
A1: Property Setup:
A2: A. Pipeline Screen | B2: • Go to Pipeline Screen and change the property status of the Property to “Closed” so it will reflect on the Property Screen.
A3: B. Process Tabs | B3: • Follow instructions in each tab (they will auto-populate after you followed the General Instructions) • Batch LOAD or UPDATE • After successful load, return to this page for validation
A4: C. Fund Validation | B4: Step 1: Check if Fund is Provided ✅ If Fund IS Provided (in the file or case description) • Proceed to the Verification Checklist (Section D). ❌ If Fund is NOT Provided 1. Email the client requesting the Fund. 2. Advise the client that: • The Property will NOT appear in the following reports: • Property Ad Hoc Report • Entity List Report • Commitment and Payment details cannot be edited. ✅ If the client provides the Fund in the email: 1. If the Fund EXISTS in the Fund screen: • Go back to the screens that require the Fund Code. • Enter the Fund Code. • Proceed to the Verification Checklist (Section D). 2. If the Fund does NOT EXIST in the Fund screen: • DO NOT add the Fund. • Inform the client that the Fund does not exist in the Fund screen. • Ask whether they would like to: • Set up the Fund • Follow Fund Setup Instructions then go back to the screens here that require Fund Code • OR Proceed without associating a Fund Code. • Advise the client about the reporting impact if no Fund is associated with the property.
B5: Step 2: If Client Does Not Provide Fund • If client confirms to proceed without Fund: • Inform client: "Setup is completed. Please note the property will not appear in reporting until a Fund is added." • If client does not respond or does not confirm: • Follow Non-response SOP then upon closure, inform client setup is completed and property will not appear in reporting until a Fund is added.
A6: D. Fund & Investment Verification Checklist (Required if Fund is provided) | B6: MRI Screen | C6: Field | D6: Required Value | E6: Impact if Incorrect | F6: Verified
B7: Financial Transaction Summary | C7: Effective Date | D7: Closing Date or Today | E7: Certain values won’t show in Property Ad Hoc | F7: FALSE
B8: Financial Transaction Summary | C8: Owner | D8: Fund Code | E8: Certain values won’t show in Property Ad Hoc | F8: FALSE
B9: Equity Installment | C9: Owner Code | D9: Fund Code | E9: Won’t show in Property Ad Hoc; Commitment/Payment can’t be edited | F9: FALSE
B10: Investor Screen | C10: Source | D10: There must always be at least one Manual Investment record. If none exists, please follow the steps below: 1. Add a New Record: Entity Code: Property Code Owner Code: Fund Code Date: Fund Close Date or Today’s Date Source: MANUAL Ownership: If only one fund → set to 1 (100%) If multiple funds → divide ownership equally Example: 2 funds → 0.50 each 2. Save the record. Check for Duplicates: If an identical record already exists (exact match for Entity, Owner, and Source), delete the newly created duplicate entry. | E10: Incomplete Setup; Duplicate record of Manual Investment will cause duplication in State Combo Report | F10: FALSE
B11: Investor Screen | C11: Source | D11: There must always be at least one Legal Entity Investment record. If none: If Legal Entity not provided: • Request from client • Advise reporting impact 1. Add New Record: Entity Code = Property Code Owner Code = Legal Entity Date = Fund Close Date or Today Source = LEGAL ENTITY Ownership: 1 (if one legal entity) If multiple→ divide equally Example: 2 legal entity → 0.50 each 2. Save Check for Duplicates: If an identical record already exists (exact match for Entity, Owner, and Source), delete the newly created duplicate entry. | E11: Won’t show in Property Ad Hoc, Entity List | F11: FALSE
B12: Property Screen | C12: Property Status | D12: In Federal deals, Property Status is included in the Load File (TXProp.vStatus) In State deals, Property Status is setup by client. If not available, advise the client of the reporting impact | E12: Won't show in Property Ad Hoc | F12: FALSE
B13: Property Screen- Legal Entity Tab | C13: Start Date | D13: Closing Date or Today | E13: Won’t show in Property Ad Hoc (Source of Quarter/Year filter in Property Ad Hoc Report) | F13: FALSE
B14: Property Screen- Legal Entity Tab | C14: Credit Type and State Credit Type | D14: Go to the Owner Screen and search for the Fund code given by the client. Note for its Tax Credit Type, put Credit Type and State Credit Type based on the Tax Credit Type you noted. | E14: Won't show in Entity List Report and State Combo Report (for State Deals) | F14: FALSE
B15: Event Dates Screen | C15: Fund Manager | D15: There should be records with: Event Type: Pipeline / Pipeline Status Fund Manager: State When a Fund is linked to the Property via Investors screen (Source = Manual), the system generates another set of Pipeline Event Type records using the Fund’s Fund Manager. If Fund Manager is blank, Check the Fund screen → Third Party Relationships → Fund Manager. Ensure the Fund Manager Start Date is on or before the Pipeline Closed date (Event Date screen: Event Type = Pipeline, Event = Closed, Date Type = Actual). | E15: Missing Fund Mgr on Event Date records | F15: FALSE
A16: E. Report Validation (Final Step – Required if Fund is Provided) | B16: If Fund is provided and Section D (Fund & Investment Verification) is completed: • Run the following reports: ✅ Property Ad Hoc Report Confirm property appears ✅ Entity List Report Confirm property appears under correct Fund (Take a screenshot of the report and paste below for additional documentation)

Sheet Property

Sheet Property - 4 (UPDATE)
A1: 1. Copy All (Ctrl+A), (Ctrl+C), and Paste Values (Ctrl+Shift+V) 2. Double-check if the address is formatted correctly: City – Sometimes incorrectly included in the State field State – Must be a two-letter abbreviation ZIP Code – In US, a standard ZIP Code is always 5 digits. If only 4 digits are provided, add a zero in front 3. Delete Gray Columns | F1: << Delete row before loading
A2: vcode | B2: vAddress1 | C2: vCity | D2: vState | E2: vZipcode
A3: {=INDEX(Property!A:A, MATCH("Prop Code", Property!A:A, 0) + 1)} -> #N/A | B3: {=IFERROR( INDEX(Property!B:B, MATCH("Address", Property!B:B, 0) + 1), INDEX(Property!D:D, MATCH("Address", Property!D:D, 0) + 1) )} -> #N/A | C3: {=IFERROR( INDEX(Property!C:C, MATCH("City ", Property!C:C, 0) + 1), INDEX(Property!E:E, MATCH("City ", Property!E:E, 0) + 1) )} -> #N/A | D3: {=IFERROR( INDEX(Property!D:D, MATCH("State", Property!D:D, 0) + 1), INDEX(Property!F:F, MATCH("State", Property!F:F, 0) + 1) )} -> #N/A | E3: {=IFERROR( INDEX(Property!E:E, MATCH("Zip Code", Property!E:E, 0) + 1), INDEX(Property!G:G, MATCH("Zip Code", Property!G:G, 0) + 1) )} -> #N/A

Sheet TXProp -5 (UPDATE)
A1: 1. Copy All (Ctrl+A), (Ctrl+C), and Paste Values (Ctrl+Shift+V) 2. Delete Gray Columns | X1: << Delete row before loading
A2: vcode | B2: vCounty | C2: iyearbuilt | D2: vLowCensus | E2: vStatus | F2: vTenancy | G2: vproptype | H2: vLocationCode | I2: vPreservation | J2: vSpecialNeeds | K2: nXIRR | L2: vUnderCensus | M2: vQct | N2: vMinCensus | O2: vScattered | P2: vDistressed | Q2: vTaxExemptBond | R2: vMezzLoanNumber | S2: vAssetManager | T2: nEffIRR | U2: vMisc3 | V2: vMisc4 | W2: vMisc5
A3: {=INDEX(Property!A:A, MATCH("Prop Code", Property!A:A, 0) + 1)} -> #N/A | B3: {=IFERROR( INDEX(Property!C:C, MATCH("County", Property!C:C, 0) + 1), INDEX(Property!I:I, MATCH("County", Property!I:I, 0) + 1) )} -> #N/A | C3: {=IFERROR(INDEX(Property!D:D,MATCH("Year Built",Property!D:D,0)+1), INDEX(Property!H:H,MATCH("Year Built",Property!H:H,0)+1))} -> #N/A | D3: {=INDEX(Property!E:E,MATCH("Hard Debt",Property!E:E,0)+1)} -> #N/A | E3: {=IFERROR(INDEX(Property!F:F,MATCH("Property Status",Property!F:F,0)+1), INDEX(Property!J:J,MATCH("Property Status",Property!J:J,0)+1))} -> #N/A | F3: {=IFERROR(INDEX(Property!G:G,MATCH("Tenancy Type",Property!G:G,0)+1), INDEX(Property!C:C,MATCH("Tenancy Type",Property!C:C,0)+1))} -> #N/A | G3: {=IFERROR(INDEX(Property!H:H,MATCH("Dev Type",Property!H:H,0)+1), INDEX(Property!A:A,MATCH("Dev Type",Property!A:A,0)+1))} -> #N/A | H3: {=IFERROR(INDEX(Property!I:I,MATCH("Location Code",Property!I:I,0)+1), INDEX(Property!B:B,MATCH("Location Code",Property!B:B,0)+1))} -> #N/A | I3: {=INDEX(Property!J:J,MATCH("Underwritting Score",Property!J:J,0)+1)} -> #N/A | J3: {=INDEX(Property!K:K,MATCH("Subsidy",Property!K:K,0)+1)} -> #N/A | K3: {=INDEX(Property!L:L,MATCH("% of Units",Property!L:L,0)+1)} -> #N/A | L3: {=INDEX(Property!M:M,MATCH("TC Bond Deal",Property!M:M,0)+1)} -> #N/A | M3: {=INDEX(Property!N:N,MATCH("Breakeven Occupancy",Property!N:N,0)+1)} -> #N/A | N3: {=INDEX(Property!O:O,MATCH("Discount to LIHTC Max",Property!O:O,0)+1)} -> #N/A | O3: {=INDEX(Property!P:P,MATCH("Discount to Market Rent",Property!P:P,0)+1)} -> #N/A | P3: {=INDEX(Property!Q:Q,MATCH("Capture Rate",Property!Q:Q,0)+1)} -> #N/A | Q3: {=INDEX(Property!R:R,MATCH("Hard Costs",Property!R:R,0)+1)} -> #N/A | R3: {=INDEX(Property!S:S,MATCH("Expense PUPA",Property!S:S,0)+1)} -> #N/A | S3: {=IFERROR( INDEX(Property!T:T, MATCH("Asset Manager",Property!T:T,0)+1), IFERROR( INDEX(Property!D:D, MATCH("Asset Manager",Property!D:D,0)+1), INDEX(Property!E:E, MATCH("Asset Manager",Property!E:E,0)+1) ) )} -> #N/A | T3: {=INDEX(Property!U:U,MATCH("Target Unit Designation Avg",Property!U:U,0)+1)} -> #N/A | U3: {=INDEX(Property!V:V,MATCH("Addt'l Third-Party Compliance",Property!V:V,0)+1)} -> #N/A | V3: {=INDEX(Property!W:W,MATCH("Basis on Which Set-Aside is Applied",Property!W:W,0)+1)} -> #N/A | W3: {=INDEX(Property!K:K,MATCH("MSA Type",Property!K:K,0)+1)} -> #N/A

Sheet TXFinanicial_IC - 6 (LOAD)
A1: 1. Copy All (Ctrl+A), (Ctrl+C), and Paste Values (Ctrl+Shift+V) 2. In dtEffective field, if 0 or 1/0/1900, put Close Date; or Date Today if close date is not provided 3. In vMisc field, search for the Fund Code in the Fund screen (Note: clients sometimes enter the Fund Name instead of the Fund Code). If all lines show 0 or NA, check the following: >Investors table, >Commitment table, >Payment table, and >Case Description for the Fund; >For Property and Fund Setup case, use the Fund Code of the fund you just setup If no records are found in any of these, leave the fields blank 4. Delete Gray Rows | F1: << Delete row before loading
A2: vCode | B2: vTransType | C2: mAmount | D2: dtEffective | E2: vMisc
A3: {=_xlfn._xlws.FILTER(Property!A:C, ISNUMBER(MATCH(Property!B:B, {"Total Fed Historic","Total Fed LIHTC","Total State Historic","Total State LIHTC","Proforma DCR","Inv. Rec. Commitment","Equity to Total Cost","Hard Debt to Total Cost","Total Guarantor Net Worth","Total Guarantor Liquidity","Hard Costs Per Unit","Orig. Operating Reserve","Orig. Other Reserve","Annual Operating Expense","Annual Debt Service","Fed Remaining Credits","State Remaining Credits","Total Fed Solar Credits","Total State Solar","Total State Certificated"},0)))} -> #VALUE! | D3: {=_xlfn.LET( _xlpm.eff, IFERROR(INDEX(Property!D:D, MATCH("Effective Date (Date of upload or close date)", Property!D:D, 0) + _xlfn.SEQUENCE(20)), ""), _xlpm.close, IFERROR(INDEX(Property!D:D, MATCH("Closing Date", Property!D:D, 0) + 1), ""), _xlpm.fallback, IF((_xlpm.close=0)+(_xlpm.close="")+(_xlpm.close="NA")+ISNA(_xlpm.close)+(_xlpm.close=DATE(1900,1,0)), TODAY(), _xlpm.close), IF((_xlpm.eff=0)+(_xlpm.eff="")+(_xlpm.eff="NA")+ISNA(_xlpm.eff)+(_xlpm.eff=DATE(1900,1,0)), _xlpm.fallback + 0*_xlfn.SEQUENCE(20), _xlpm.eff) )} -> 46232 | E3: {=_xlfn.LET( _xlpm.primary, IFERROR(INDEX(Property!E:E, MATCH("Fund Code", Property!E:E, 0) + _xlfn.SEQUENCE(20)), ""), _xlpm.fallback, IFERROR(INDEX(Property!A:A, MATCH("Fund", Property!A:A, 0) + 1), ""), IF((_xlpm.primary=0)+(_xlpm.primary="")+(_xlpm.primary="NA")+(_xlpm.primary="#N/A"), _xlpm.fallback, _xlpm.primary) )}
D4: 46232
D5: 46232
D6: 46232
D7: 46232
D8: 46232
D9: 46232
D10: 46232
D11: 46232
D12: 46232
D13: 46232
D14: 46232
D15: 46232
... D22: 46232

Sheet Event_Dates - 7 (LOAD)
A1: 1. Copy All (Ctrl+A), (Ctrl+C), and Paste Values (Ctrl+Shift+V) 2. Delete Gray Rows | G1: << Delete row before loading
A2: vCode | B2: vEventType | C2: vEvent | D2: vDateType | E2: dtEvent | F2: dtEntry
A3: {=INDEX(Property!A:A, MATCH("Prop Code", Property!A:A, 0) + 1)} -> #N/A | B3: {=IFERROR( _xlfn._xlws.FILTER(Property!H:K, ISNUMBER(MATCH(Property!H:H, {"Lease Up","Call","Construction","Compliance","Pipeline","Pipeline Status","Asset Management","Acquisition","Fund","Property","Construction","Put"},0))), _xlfn._xlws.FILTER(Property!B:E, ISNUMBER(MATCH(Property!B:B, {"Lease Up","Call","Construction","Compliance","Pipeline","Pipeline Status","Asset Management","Acquisition","Fund","Property","Construction","Put"},0))) )} -> #VALUE! | F3: =TODAY() -> 46232
A4: {=INDEX(Property!A:A, MATCH("Prop Code", Property!A:A, 0) + 1)} -> #N/A | F4: =TODAY() -> 46232
A5: {=INDEX(Property!A:A, MATCH("Prop Code", Property!A:A, 0) + 1)} -> #N/A | F5: =TODAY() -> 46232

Sheet Commitment - 8 (LOAD)
A1: 1. Copy All (Ctrl+A), (Ctrl+C), and Paste Values (Ctrl+Shift+V) 2. In vOwnerCode, search for the Fund Code in the Fund screen (Note: clients sometimes enter the Fund Name instead of the Fund Code). If all lines show 0 or NA, check the following: >Investors table, >TXFinancial_IC table, >Payment table, and >Case Description for the Fund; If no records are found in any of these, leave the fields blank 3. In dtCommitment field, if 0 or 1/0/1900, put Close Date; or Date Today if close date is not provided 4. Delete gray rows (rows with no amount or rows with past dtDue) 5. Fill vInstallNmbr with 1,2,3, and so on | I1: << Delete row before loading
A2: vCode | B2: vOwnerCode | C2: dtCommitment | D2: vInstallNmbr | E2: mAmount | F2: vType | G2: dtDue | H2: vCreditType
A3: {=INDEX(Property!A:A, MATCH("Prop Code", Property!A:A, 0) + 1)} -> #N/A | B3: {=_xlfn.LET( _xlpm.primary, IFERROR(INDEX(Property!B:B, MATCH("Fund Code", Property!B:B, 0) + 1), ""), _xlpm.fallback, IFERROR(INDEX(Property!A:A, MATCH("Fund", Property!A:A, 0) + 1), ""), IF( (_xlpm.primary=0)+(_xlpm.primary="")+(_xlpm.primary="NA")+(_xlpm.primary="#N/A"), _xlpm.fallback, _xlpm.primary ) )} | C3: {=_xlfn.LET( _xlpm.d, IFERROR(INDEX(Property!C:C, MATCH("Date", Property!C:C, 0) + 1), ""), _xlpm.c, IFERROR(INDEX(Property!D:D, MATCH("Closing Date", Property!D:D, 0) + 1), ""), IF( OR(_xlpm.d="", _xlpm.d=0, _xlpm.d="NA", ISNA(_xlpm.d), _xlpm.d=DATE(1900,1,0)), IF(OR(_xlpm.c="", _xlpm.c=0, _xlpm.c="NA", ISNA(_xlpm.c), _xlpm.c=DATE(1900,1,0)), TODAY(), _xlpm.c), _xlpm.d ) )} -> 46232 | E3: {=INDEX(Property!E:E, MATCH("Amount", Property!E:E, 0) + _xlfn.SEQUENCE(2))} -> #N/A | F3: {=INDEX(Property!F:F, MATCH("Type", Property!F:F, 0) + _xlfn.SEQUENCE(2))} -> #N/A | H3: {=INDEX(Property!G:G, MATCH("Credit Type", Property!G:G, 0) + _xlfn.SEQUENCE(2))} -> #N/A
A4: {=INDEX(Property!A:A, MATCH("Prop Code", Property!A:A, 0) + 1)} -> #N/A | B4: {=_xlfn.LET( _xlpm.primary, IFERROR(INDEX(Property!B:B, MATCH("Fund Code", Property!B:B, 0) + 1), ""), _xlpm.fallback, IFERROR(INDEX(Property!A:A, MATCH("Fund", Property!A:A, 0) + 1), ""), IF( (_xlpm.primary=0)+(_xlpm.primary="")+(_xlpm.primary="NA")+(_xlpm.primary="#N/A"), _xlpm.fallback, _xlpm.primary ) )} | C4: {=_xlfn.LET( _xlpm.d, IFERROR(INDEX(Property!C:C, MATCH("Date", Property!C:C, 0) + 1), ""), _xlpm.c, IFERROR(INDEX(Property!D:D, MATCH("Closing Date", Property!D:D, 0) + 1), ""), IF( OR(_xlpm.d="", _xlpm.d=0, _xlpm.d="NA", ISNA(_xlpm.d), _xlpm.d=DATE(1900,1,0)), IF(OR(_xlpm.c="", _xlpm.c=0, _xlpm.c="NA", ISNA(_xlpm.c), _xlpm.c=DATE(1900,1,0)), TODAY(), _xlpm.c), _xlpm.d ) )} -> 46232 | E4: #N/A | F4: #N/A | H4: #N/A
A5: {=INDEX(Property!A:A, MATCH("Prop Code", Property!A:A, 0) + 1)} -> #N/A | B5: {=_xlfn.LET( _xlpm.primary, IFERROR(INDEX(Property!B:B, MATCH("Fund Code", Property!B:B, 0) + 1), ""), _xlpm.fallback, IFERROR(INDEX(Property!A:A, MATCH("Fund", Property!A:A, 0) + 1), ""), IF( (_xlpm.primary=0)+(_xlpm.primary="")+(_xlpm.primary="NA")+(_xlpm.primary="#N/A"), _xlpm.fallback, _xlpm.primary ) )} | C5: {=_xlfn.LET( _xlpm.d, IFERROR(INDEX(Property!C:C, MATCH("Date", Property!C:C, 0) + 1), ""), _xlpm.c, IFERROR(INDEX(Property!D:D, MATCH("Closing Date", Property!D:D, 0) + 1), ""), IF( OR(_xlpm.d="", _xlpm.d=0, _xlpm.d="NA", ISNA(_xlpm.d), _xlpm.d=DATE(1900,1,0)), IF(OR(_xlpm.c="", _xlpm.c=0, _xlpm.c="NA", ISNA(_xlpm.c), _xlpm.c=DATE(1900,1,0)), TODAY(), _xlpm.c), _xlpm.d ) )} -> 46232 | E5: {=IFERROR( INDEX(Property!F:F, MATCH("Amount", Property!F:F, 0) + _xlfn.SEQUENCE(32)), INDEX(Property!B:B, MATCH("Contribution Amount", Property!B:B, 0) + _xlfn.SEQUENCE(32)))} -> #N/A | F5: {=IFERROR( INDEX(Property!G:G, MATCH("Type", Property!G:G, 0) + _xlfn.SEQUENCE(32)), INDEX(Property!C:C, MATCH("Type", Property!C:C, 0) + _xlfn.SEQUENCE(32)) )} -> #N/A | G5: {=IFERROR( IF(INDEX(Property!A:A, MATCH("Date", Property!A:A, 0) + _xlfn.SEQUENCE(32))="", "", IF(INDEX(Property!A:A, MATCH("Date", Property!A:A, 0) + _xlfn.SEQUENCE(32))=0, "", INDEX(Property!A:A, MATCH("Date", Property!A:A, 0) + _xlfn.SEQUENCE(32)))), IF(INDEX(Property!D:D, MATCH("Projected Date", Property!D:D, 0) + _xlfn.SEQUENCE(32))="", "", IF(INDEX(Property!D:D, MATCH("Projected Date", Property!D:D, 0) + _xlfn.SEQUENCE(32))=0, "", INDEX(Property!D:D, MATCH("Projected Date", Property!D:D, 0) + _xlfn.SEQUENCE(32)))) )} -> #N/A | H5: {=IFERROR( INDEX(Property!D:D, MATCH("Credit Type", Property!D:D, 0) + _xlfn.SEQUENCE(32)), INDEX(Property!H:H, MATCH("Credit Type", Property!H:H, 0) + _xlfn.SEQUENCE(32)) )} -> #N/A
A6: {=INDEX(Property!A:A, MATCH("Prop Code", Property!A:A, 0) + 1)} -> #N/A | B6: {=_xlfn.LET( _xlpm.primary, IFERROR(INDEX(Property!B:B, MATCH("Fund Code", Property!B:B, 0) + 1), ""), _xlpm.fallback, IFERROR(INDEX(Property!A:A, MATCH("Fund", Property!A:A, 0) + 1), ""), IF( (_xlpm.primary=0)+(_xlpm.primary="")+(_xlpm.primary="NA")+(_xlpm.primary="#N/A"), _xlpm.fallback, _xlpm.primary ) )} | C6: {=_xlfn.LET( _xlpm.d, IFERROR(INDEX(Property!C:C, MATCH("Date", Property!C:C, 0) + 1), ""), _xlpm.c, IFERROR(INDEX(Property!D:D, MATCH("Closing Date", Property!D:D, 0) + 1), ""), IF( OR(_xlpm.d="", _xlpm.d=0, _xlpm.d="NA", ISNA(_xlpm.d), _xlpm.d=DATE(1900,1,0)), IF(OR(_xlpm.c="", _xlpm.c=0, _xlpm.c="NA", ISNA(_xlpm.c), _xlpm.c=DATE(1900,1,0)), TODAY(), _xlpm.c), _xlpm.d ) )} -> 46232 | E6: #N/A | F6: #N/A | G6: #N/A | H6: #N/A
A7: {=INDEX(Property!A:A, MATCH("Prop Code", Property!A:A, 0) + 1)} -> #N/A | B7: {=_xlfn.LET( _xlpm.primary, IFERROR(INDEX(Property!B:B, MATCH("Fund Code", Property!B:B, 0) + 1), ""), _xlpm.fallback, IFERROR(INDEX(Property!A:A, MATCH("Fund", Property!A:A, 0) + 1), ""), IF( (_xlpm.primary=0)+(_xlpm.primary="")+(_xlpm.primary="NA")+(_xlpm.primary="#N/A"), _xlpm.fallback, _xlpm.primary ) )} | C7: {=_xlfn.LET( _xlpm.d, IFERROR(INDEX(Property!C:C, MATCH("Date", Property!C:C, 0) + 1), ""), _xlpm.c, IFERROR(INDEX(Property!D:D, MATCH("Closing Date", Property!D:D, 0) + 1), ""), IF( OR(_xlpm.d="", _xlpm.d=0, _xlpm.d="NA", ISNA(_xlpm.d), _xlpm.d=DATE(1900,1,0)), IF(OR(_xlpm.c="", _xlpm.c=0, _xlpm.c="NA", ISNA(_xlpm.c), _xlpm.c=DATE(1900,1,0)), TODAY(), _xlpm.c), _xlpm.d ) )} -> 46232 | E7: #N/A | F7: #N/A | G7: #N/A | H7: #N/A
A8: {=INDEX(Property!A:A, MATCH("Prop Code", Property!A:A, 0) + 1)} -> #N/A | B8: {=_xlfn.LET( _xlpm.primary, IFERROR(INDEX(Property!B:B, MATCH("Fund Code", Property!B:B, 0) + 1), ""), _xlpm.fallback, IFERROR(INDEX(Property!A:A, MATCH("Fund", Property!A:A, 0) + 1), ""), IF( (_xlpm.primary=0)+(_xlpm.primary="")+(_xlpm.primary="NA")+(_xlpm.primary="#N/A"), _xlpm.fallback, _xlpm.primary ) )} | C8: {=_xlfn.LET( _xlpm.d, IFERROR(INDEX(Property!C:C, MATCH("Date", Property!C:C, 0) + 1), ""), _xlpm.c, IFERROR(INDEX(Property!D:D, MATCH("Closing Date", Property!D:D, 0) + 1), ""), IF( OR(_xlpm.d="", _xlpm.d=0, _xlpm.d="NA", ISNA(_xlpm.d), _xlpm.d=DATE(1900,1,0)), IF(OR(_xlpm.c="", _xlpm.c=0, _xlpm.c="NA", ISNA(_xlpm.c), _xlpm.c=DATE(1900,1,0)), TODAY(), _xlpm.c), _xlpm.d ) )} -> 46232 | E8: #N/A | F8: #N/A | G8: #N/A | H8: #N/A
A9: {=INDEX(Property!A:A, MATCH("Prop Code", Property!A:A, 0) + 1)} -> #N/A | B9: {=_xlfn.LET( _xlpm.primary, IFERROR(INDEX(Property!B:B, MATCH("Fund Code", Property!B:B, 0) + 1), ""), _xlpm.fallback, IFERROR(INDEX(Property!A:A, MATCH("Fund", Property!A:A, 0) + 1), ""), IF( (_xlpm.primary=0)+(_xlpm.primary="")+(_xlpm.primary="NA")+(_xlpm.primary="#N/A"), _xlpm.fallback, _xlpm.primary ) )} | C9: {=_xlfn.LET( _xlpm.d, IFERROR(INDEX(Property!C:C, MATCH("Date", Property!C:C, 0) + 1), ""), _xlpm.c, IFERROR(INDEX(Property!D:D, MATCH("Closing Date", Property!D:D, 0) + 1), ""), IF( OR(_xlpm.d="", _xlpm.d=0, _xlpm.d="NA", ISNA(_xlpm.d), _xlpm.d=DATE(1900,1,0)), IF(OR(_xlpm.c="", _xlpm.c=0, _xlpm.c="NA", ISNA(_xlpm.c), _xlpm.c=DATE(1900,1,0)), TODAY(), _xlpm.c), _xlpm.d ) )} -> 46232 | E9: #N/A | F9: #N/A | G9: #N/A | H9: #N/A
A10: {=INDEX(Property!A:A, MATCH("Prop Code", Property!A:A, 0) + 1)} -> #N/A | B10: {=_xlfn.LET( _xlpm.primary, IFERROR(INDEX(Property!B:B, MATCH("Fund Code", Property!B:B, 0) + 1), ""), _xlpm.fallback, IFERROR(INDEX(Property!A:A, MATCH("Fund", Property!A:A, 0) + 1), ""), IF( (_xlpm.primary=0)+(_xlpm.primary="")+(_xlpm.primary="NA")+(_xlpm.primary="#N/A"), _xlpm.fallback, _xlpm.primary ) )} | C10: {=_xlfn.LET( _xlpm.d, IFERROR(INDEX(Property!C:C, MATCH("Date", Property!C:C, 0) + 1), ""), _xlpm.c, IFERROR(INDEX(Property!D:D, MATCH("Closing Date", Property!D:D, 0) + 1), ""), IF( OR(_xlpm.d="", _xlpm.d=0, _xlpm.d="NA", ISNA(_xlpm.d), _xlpm.d=DATE(1900,1,0)), IF(OR(_xlpm.c="", _xlpm.c=0, _xlpm.c="NA", ISNA(_xlpm.c), _xlpm.c=DATE(1900,1,0)), TODAY(), _xlpm.c), _xlpm.d ) )} -> 46232 | E10: #N/A | F10: #N/A | G10: #N/A | H10: #N/A
A11: {=INDEX(Property!A:A, MATCH("Prop Code", Property!A:A, 0) + 1)} -> #N/A | B11: {=_xlfn.LET( _xlpm.primary, IFERROR(INDEX(Property!B:B, MATCH("Fund Code", Property!B:B, 0) + 1), ""), _xlpm.fallback, IFERROR(INDEX(Property!A:A, MATCH("Fund", Property!A:A, 0) + 1), ""), IF( (_xlpm.primary=0)+(_xlpm.primary="")+(_xlpm.primary="NA")+(_xlpm.primary="#N/A"), _xlpm.fallback, _xlpm.primary ) )} | C11: {=_xlfn.LET( _xlpm.d, IFERROR(INDEX(Property!C:C, MATCH("Date", Property!C:C, 0) + 1), ""), _xlpm.c, IFERROR(INDEX(Property!D:D, MATCH("Closing Date", Property!D:D, 0) + 1), ""), IF( OR(_xlpm.d="", _xlpm.d=0, _xlpm.d="NA", ISNA(_xlpm.d), _xlpm.d=DATE(1900,1,0)), IF(OR(_xlpm.c="", _xlpm.c=0, _xlpm.c="NA", ISNA(_xlpm.c), _xlpm.c=DATE(1900,1,0)), TODAY(), _xlpm.c), _xlpm.d ) )} -> 46232 | E11: #N/A | F11: #N/A | G11: #N/A | H11: #N/A
A12: {=INDEX(Property!A:A, MATCH("Prop Code", Property!A:A, 0) + 1)} -> #N/A | B12: {=_xlfn.LET( _xlpm.primary, IFERROR(INDEX(Property!B:B, MATCH("Fund Code", Property!B:B, 0) + 1), ""), _xlpm.fallback, IFERROR(INDEX(Property!A:A, MATCH("Fund", Property!A:A, 0) + 1), ""), IF( (_xlpm.primary=0)+(_xlpm.primary="")+(_xlpm.primary="NA")+(_xlpm.primary="#N/A"), _xlpm.fallback, _xlpm.primary ) )} | C12: {=_xlfn.LET( _xlpm.d, IFERROR(INDEX(Property!C:C, MATCH("Date", Property!C:C, 0) + 1), ""), _xlpm.c, IFERROR(INDEX(Property!D:D, MATCH("Closing Date", Property!D:D, 0) + 1), ""), IF( OR(_xlpm.d="", _xlpm.d=0, _xlpm.d="NA", ISNA(_xlpm.d), _xlpm.d=DATE(1900,1,0)), IF(OR(_xlpm.c="", _xlpm.c=0, _xlpm.c="NA", ISNA(_xlpm.c), _xlpm.c=DATE(1900,1,0)), TODAY(), _xlpm.c), _xlpm.d ) )} -> 46232 | E12: #N/A | F12: #N/A | G12: #N/A | H12: #N/A
A13: {=INDEX(Property!A:A, MATCH("Prop Code", Property!A:A, 0) + 1)} -> #N/A | B13: {=_xlfn.LET( _xlpm.primary, IFERROR(INDEX(Property!B:B, MATCH("Fund Code", Property!B:B, 0) + 1), ""), _xlpm.fallback, IFERROR(INDEX(Property!A:A, MATCH("Fund", Property!A:A, 0) + 1), ""), IF( (_xlpm.primary=0)+(_xlpm.primary="")+(_xlpm.primary="NA")+(_xlpm.primary="#N/A"), _xlpm.fallback, _xlpm.primary ) )} | C13: {=_xlfn.LET( _xlpm.d, IFERROR(INDEX(Property!C:C, MATCH("Date", Property!C:C, 0) + 1), ""), _xlpm.c, IFERROR(INDEX(Property!D:D, MATCH("Closing Date", Property!D:D, 0) + 1), ""), IF( OR(_xlpm.d="", _xlpm.d=0, _xlpm.d="NA", ISNA(_xlpm.d), _xlpm.d=DATE(1900,1,0)), IF(OR(_xlpm.c="", _xlpm.c=0, _xlpm.c="NA", ISNA(_xlpm.c), _xlpm.c=DATE(1900,1,0)), TODAY(), _xlpm.c), _xlpm.d ) )} -> 46232 | E13: #N/A | F13: #N/A | G13: #N/A | H13: #N/A
A14: {=INDEX(Property!A:A, MATCH("Prop Code", Property!A:A, 0) + 1)} -> #N/A | B14: {=_xlfn.LET( _xlpm.primary, IFERROR(INDEX(Property!B:B, MATCH("Fund Code", Property!B:B, 0) + 1), ""), _xlpm.fallback, IFERROR(INDEX(Property!A:A, MATCH("Fund", Property!A:A, 0) + 1), ""), IF( (_xlpm.primary=0)+(_xlpm.primary="")+(_xlpm.primary="NA")+(_xlpm.primary="#N/A"), _xlpm.fallback, _xlpm.primary ) )} | C14: {=_xlfn.LET( _xlpm.d, IFERROR(INDEX(Property!C:C, MATCH("Date", Property!C:C, 0) + 1), ""), _xlpm.c, IFERROR(INDEX(Property!D:D, MATCH("Closing Date", Property!D:D, 0) + 1), ""), IF( OR(_xlpm.d="", _xlpm.d=0, _xlpm.d="NA", ISNA(_xlpm.d), _xlpm.d=DATE(1900,1,0)), IF(OR(_xlpm.c="", _xlpm.c=0, _xlpm.c="NA", ISNA(_xlpm.c), _xlpm.c=DATE(1900,1,0)), TODAY(), _xlpm.c), _xlpm.d ) )} -> 46232 | E14: #N/A | F14: #N/A | G14: #N/A | H14: #N/A
A15: {=INDEX(Property!A:A, MATCH("Prop Code", Property!A:A, 0) + 1)} -> #N/A | B15: {=_xlfn.LET( _xlpm.primary, IFERROR(INDEX(Property!B:B, MATCH("Fund Code", Property!B:B, 0) + 1), ""), _xlpm.fallback, IFERROR(INDEX(Property!A:A, MATCH("Fund", Property!A:A, 0) + 1), ""), IF( (_xlpm.primary=0)+(_xlpm.primary="")+(_xlpm.primary="NA")+(_xlpm.primary="#N/A"), _xlpm.fallback, _xlpm.primary ) )} | C15: {=_xlfn.LET( _xlpm.d, IFERROR(INDEX(Property!C:C, MATCH("Date", Property!C:C, 0) + 1), ""), _xlpm.c, IFERROR(INDEX(Property!D:D, MATCH("Closing Date", Property!D:D, 0) + 1), ""), IF( OR(_xlpm.d="", _xlpm.d=0, _xlpm.d="NA", ISNA(_xlpm.d), _xlpm.d=DATE(1900,1,0)), IF(OR(_xlpm.c="", _xlpm.c=0, _xlpm.c="NA", ISNA(_xlpm.c), _xlpm.c=DATE(1900,1,0)), TODAY(), _xlpm.c), _xlpm.d ) )} -> 46232 | E15: #N/A | F15: #N/A | G15: #N/A | H15: #N/A
A16: {=INDEX(Property!A:A, MATCH("Prop Code", Property!A:A, 0) + 1)} -> #N/A | B16: {=_xlfn.LET( _xlpm.primary, IFERROR(INDEX(Property!B:B, MATCH("Fund Code", Property!B:B, 0) + 1), ""), _xlpm.fallback, IFERROR(INDEX(Property!A:A, MATCH("Fund", Property!A:A, 0) + 1), ""), IF( (_xlpm.primary=0)+(_xlpm.primary="")+(_xlpm.primary="NA")+(_xlpm.primary="#N/A"), _xlpm.fallback, _xlpm.primary ) )} | C16: {=_xlfn.LET( _xlpm.d, IFERROR(INDEX(Property!C:C, MATCH("Date", Property!C:C, 0) + 1), ""), _xlpm.c, IFERROR(INDEX(Property!D:D, MATCH("Closing Date", Property!D:D, 0) + 1), ""), IF( OR(_xlpm.d="", _xlpm.d=0, _xlpm.d="NA", ISNA(_xlpm.d), _xlpm.d=DATE(1900,1,0)), IF(OR(_xlpm.c="", _xlpm.c=0, _xlpm.c="NA", ISNA(_xlpm.c), _xlpm.c=DATE(1900,1,0)), TODAY(), _xlpm.c), _xlpm.d ) )} -> 46232 | E16: #N/A | F16: #N/A | G16: #N/A | H16: #N/A
A17: {=INDEX(Property!A:A, MATCH("Prop Code", Property!A:A, 0) + 1)} -> #N/A | B17: {=_xlfn.LET( _xlpm.primary, IFERROR(INDEX(Property!B:B, MATCH("Fund Code", Property!B:B, 0) + 1), ""), _xlpm.fallback, IFERROR(INDEX(Property!A:A, MATCH("Fund", Property!A:A, 0) + 1), ""), IF( (_xlpm.primary=0)+(_xlpm.primary="")+(_xlpm.primary="NA")+(_xlpm.primary="#N/A"), _xlpm.fallback, _xlpm.primary ) )} | C17: {=_xlfn.LET( _xlpm.d, IFERROR(INDEX(Property!C:C, MATCH("Date", Property!C:C, 0) + 1), ""), _xlpm.c, IFERROR(INDEX(Property!D:D, MATCH("Closing Date", Property!D:D, 0) + 1), ""), IF( OR(_xlpm.d="", _xlpm.d=0, _xlpm.d="NA", ISNA(_xlpm.d), _xlpm.d=DATE(1900,1,0)), IF(OR(_xlpm.c="", _xlpm.c=0, _xlpm.c="NA", ISNA(_xlpm.c), _xlpm.c=DATE(1900,1,0)), TODAY(), _xlpm.c), _xlpm.d ) )} -> 46232 | E17: #N/A | F17: #N/A | G17: #N/A | H17: #N/A
... A36: {=INDEX(Property!A:A, MATCH("Prop Code", Property!A:A, 0) + 1)} -> #N/A | B36: {=_xlfn.LET( _xlpm.primary, IFERROR(INDEX(Property!B:B, MATCH("Fund Code", Property!B:B, 0) + 1), ""), _xlpm.fallback, IFERROR(INDEX(Property!A:A, MATCH("Fund", Property!A:A, 0) + 1), ""), IF( (_xlpm.primary=0)+(_xlpm.primary="")+(_xlpm.primary="NA")+(_xlpm.primary="#N/A"), _xlpm.fallback, _xlpm.primary ) )} | C36: {=_xlfn.LET( _xlpm.d, IFERROR(INDEX(Property!C:C, MATCH("Date", Property!C:C, 0) + 1), ""), _xlpm.c, IFERROR(INDEX(Property!D:D, MATCH("Closing Date", Property!D:D, 0) + 1), ""), IF( OR(_xlpm.d="", _xlpm.d=0, _xlpm.d="NA", ISNA(_xlpm.d), _xlpm.d=DATE(1900,1,0)), IF(OR(_xlpm.c="", _xlpm.c=0, _xlpm.c="NA", ISNA(_xlpm.c), _xlpm.c=DATE(1900,1,0)), TODAY(), _xlpm.c), _xlpm.d ) )} -> 46232 | E36: #N/A | F36: #N/A | G36: #N/A | H36: #N/A

Sheet Payment - 9 (LOAD)
A1: 1. Copy All (Ctrl+A), (Ctrl+C), and Paste Values (Ctrl+Shift+V) 2. In vOwnerCode, search for the Fund Code in the Fund screen (Note: clients sometimes enter the Fund Name instead of the Fund Code). If all lines show 0 or NA, check the following: >Investors table, >TXFinancial_IC table, >Commitment table, and >Case Description for the Fund; If no records are found in any of these, leave the fields blank 3. Delete gray rows (rows with no amount or rows with past dtPayment) 4. Fill vInstallment with 1,2,3, and so on | H1: << Delete row before loading
A2: vCode | B2: vOwnerCode | C2: dtPayment | D2: vInstallment | E2: mAmountPaid | F2: vReason | G2: vCreditType
A3: {=INDEX(Property!A:A, MATCH("Prop Code", Property!A:A, 0) + 1)} -> #N/A | B3: {=_xlfn.LET( _xlpm.primary, IFERROR(INDEX(Property!B:B, MATCH("Fund Code", Property!B:B, 0) + 1), ""), _xlpm.fallback, IFERROR(INDEX(Property!A:A, MATCH("Fund", Property!A:A, 0) + 1), ""), IF( (_xlpm.primary=0)+(_xlpm.primary="")+(_xlpm.primary="NA")+(_xlpm.primary="#N/A"), _xlpm.fallback, _xlpm.primary ) )} | C3: {=IFERROR( IF(INDEX(Property!A:A, MATCH("Date", Property!A:A, 0) + _xlfn.SEQUENCE(32))="", "", IF(INDEX(Property!A:A, MATCH("Date", Property!A:A, 0) + _xlfn.SEQUENCE(32))=0, "", INDEX(Property!A:A, MATCH("Date", Property!A:A, 0) + _xlfn.SEQUENCE(32)))), IF(INDEX(Property!D:D, MATCH("Projected Date", Property!D:D, 0) + _xlfn.SEQUENCE(32))="", "", IF(INDEX(Property!D:D, MATCH("Projected Date", Property!D:D, 0) + _xlfn.SEQUENCE(32))=0, "", INDEX(Property!D:D, MATCH("Projected Date", Property!D:D, 0) + _xlfn.SEQUENCE(32)))) )} -> #N/A | E3: {=IFERROR( INDEX(Property!F:F, MATCH("Amount", Property!F:F, 0) + _xlfn.SEQUENCE(32)), INDEX(Property!B:B, MATCH("Contribution Amount", Property!B:B, 0) + _xlfn.SEQUENCE(32)))} -> #N/A | F3: {=IFERROR( INDEX(Property!G:G, MATCH("Type", Property!G:G, 0) + _xlfn.SEQUENCE(32)), INDEX(Property!C:C, MATCH("Type", Property!C:C, 0) + _xlfn.SEQUENCE(32)) )} -> #N/A | G3: {=IFERROR( INDEX(Property!D:D, MATCH("Credit Type", Property!D:D, 0) + _xlfn.SEQUENCE(32)), INDEX(Property!H:H, MATCH("Credit Type", Property!H:H, 0) + _xlfn.SEQUENCE(32)) )} -> #N/A
A4: {=INDEX(Property!A:A, MATCH("Prop Code", Property!A:A, 0) + 1)} -> #N/A | B4: {=_xlfn.LET( _xlpm.primary, IFERROR(INDEX(Property!B:B, MATCH("Fund Code", Property!B:B, 0) + 1), ""), _xlpm.fallback, IFERROR(INDEX(Property!A:A, MATCH("Fund", Property!A:A, 0) + 1), ""), IF( (_xlpm.primary=0)+(_xlpm.primary="")+(_xlpm.primary="NA")+(_xlpm.primary="#N/A"), _xlpm.fallback, _xlpm.primary ) )} | C4: #N/A | E4: #N/A | F4: #N/A | G4: #N/A
A5: {=INDEX(Property!A:A, MATCH("Prop Code", Property!A:A, 0) + 1)} -> #N/A | B5: {=_xlfn.LET( _xlpm.primary, IFERROR(INDEX(Property!B:B, MATCH("Fund Code", Property!B:B, 0) + 1), ""), _xlpm.fallback, IFERROR(INDEX(Property!A:A, MATCH("Fund", Property!A:A, 0) + 1), ""), IF( (_xlpm.primary=0)+(_xlpm.primary="")+(_xlpm.primary="NA")+(_xlpm.primary="#N/A"), _xlpm.fallback, _xlpm.primary ) )} | C5: #N/A | E5: #N/A | F5: #N/A | G5: #N/A
A6: {=INDEX(Property!A:A, MATCH("Prop Code", Property!A:A, 0) + 1)} -> #N/A | B6: {=_xlfn.LET( _xlpm.primary, IFERROR(INDEX(Property!B:B, MATCH("Fund Code", Property!B:B, 0) + 1), ""), _xlpm.fallback, IFERROR(INDEX(Property!A:A, MATCH("Fund", Property!A:A, 0) + 1), ""), IF( (_xlpm.primary=0)+(_xlpm.primary="")+(_xlpm.primary="NA")+(_xlpm.primary="#N/A"), _xlpm.fallback, _xlpm.primary ) )} | C6: #N/A | E6: #N/A | F6: #N/A | G6: #N/A
A7: {=INDEX(Property!A:A, MATCH("Prop Code", Property!A:A, 0) + 1)} -> #N/A | B7: {=_xlfn.LET( _xlpm.primary, IFERROR(INDEX(Property!B:B, MATCH("Fund Code", Property!B:B, 0) + 1), ""), _xlpm.fallback, IFERROR(INDEX(Property!A:A, MATCH("Fund", Property!A:A, 0) + 1), ""), IF( (_xlpm.primary=0)+(_xlpm.primary="")+(_xlpm.primary="NA")+(_xlpm.primary="#N/A"), _xlpm.fallback, _xlpm.primary ) )} | C7: #N/A | E7: #N/A | F7: #N/A | G7: #N/A
A8: {=INDEX(Property!A:A, MATCH("Prop Code", Property!A:A, 0) + 1)} -> #N/A | B8: {=_xlfn.LET( _xlpm.primary, IFERROR(INDEX(Property!B:B, MATCH("Fund Code", Property!B:B, 0) + 1), ""), _xlpm.fallback, IFERROR(INDEX(Property!A:A, MATCH("Fund", Property!A:A, 0) + 1), ""), IF( (_xlpm.primary=0)+(_xlpm.primary="")+(_xlpm.primary="NA")+(_xlpm.primary="#N/A"), _xlpm.fallback, _xlpm.primary ) )} | C8: #N/A | E8: #N/A | F8: #N/A | G8: #N/A
A9: {=INDEX(Property!A:A, MATCH("Prop Code", Property!A:A, 0) + 1)} -> #N/A | B9: {=_xlfn.LET( _xlpm.primary, IFERROR(INDEX(Property!B:B, MATCH("Fund Code", Property!B:B, 0) + 1), ""), _xlpm.fallback, IFERROR(INDEX(Property!A:A, MATCH("Fund", Property!A:A, 0) + 1), ""), IF( (_xlpm.primary=0)+(_xlpm.primary="")+(_xlpm.primary="NA")+(_xlpm.primary="#N/A"), _xlpm.fallback, _xlpm.primary ) )} | C9: #N/A | E9: #N/A | F9: #N/A | G9: #N/A
A10: {=INDEX(Property!A:A, MATCH("Prop Code", Property!A:A, 0) + 1)} -> #N/A | B10: {=_xlfn.LET( _xlpm.primary, IFERROR(INDEX(Property!B:B, MATCH("Fund Code", Property!B:B, 0) + 1), ""), _xlpm.fallback, IFERROR(INDEX(Property!A:A, MATCH("Fund", Property!A:A, 0) + 1), ""), IF( (_xlpm.primary=0)+(_xlpm.primary="")+(_xlpm.primary="NA")+(_xlpm.primary="#N/A"), _xlpm.fallback, _xlpm.primary ) )} | C10: #N/A | E10: #N/A | F10: #N/A | G10: #N/A
A11: {=INDEX(Property!A:A, MATCH("Prop Code", Property!A:A, 0) + 1)} -> #N/A | B11: {=_xlfn.LET( _xlpm.primary, IFERROR(INDEX(Property!B:B, MATCH("Fund Code", Property!B:B, 0) + 1), ""), _xlpm.fallback, IFERROR(INDEX(Property!A:A, MATCH("Fund", Property!A:A, 0) + 1), ""), IF( (_xlpm.primary=0)+(_xlpm.primary="")+(_xlpm.primary="NA")+(_xlpm.primary="#N/A"), _xlpm.fallback, _xlpm.primary ) )} | C11: #N/A | E11: #N/A | F11: #N/A | G11: #N/A
A12: {=INDEX(Property!A:A, MATCH("Prop Code", Property!A:A, 0) + 1)} -> #N/A | B12: {=_xlfn.LET( _xlpm.primary, IFERROR(INDEX(Property!B:B, MATCH("Fund Code", Property!B:B, 0) + 1), ""), _xlpm.fallback, IFERROR(INDEX(Property!A:A, MATCH("Fund", Property!A:A, 0) + 1), ""), IF( (_xlpm.primary=0)+(_xlpm.primary="")+(_xlpm.primary="NA")+(_xlpm.primary="#N/A"), _xlpm.fallback, _xlpm.primary ) )} | C12: #N/A | E12: #N/A | F12: #N/A | G12: #N/A
A13: {=INDEX(Property!A:A, MATCH("Prop Code", Property!A:A, 0) + 1)} -> #N/A | B13: {=_xlfn.LET( _xlpm.primary, IFERROR(INDEX(Property!B:B, MATCH("Fund Code", Property!B:B, 0) + 1), ""), _xlpm.fallback, IFERROR(INDEX(Property!A:A, MATCH("Fund", Property!A:A, 0) + 1), ""), IF( (_xlpm.primary=0)+(_xlpm.primary="")+(_xlpm.primary="NA")+(_xlpm.primary="#N/A"), _xlpm.fallback, _xlpm.primary ) )} | C13: #N/A | E13: #N/A | F13: #N/A | G13: #N/A
A14: {=INDEX(Property!A:A, MATCH("Prop Code", Property!A:A, 0) + 1)} -> #N/A | B14: {=_xlfn.LET( _xlpm.primary, IFERROR(INDEX(Property!B:B, MATCH("Fund Code", Property!B:B, 0) + 1), ""), _xlpm.fallback, IFERROR(INDEX(Property!A:A, MATCH("Fund", Property!A:A, 0) + 1), ""), IF( (_xlpm.primary=0)+(_xlpm.primary="")+(_xlpm.primary="NA")+(_xlpm.primary="#N/A"), _xlpm.fallback, _xlpm.primary ) )} | C14: #N/A | E14: #N/A | F14: #N/A | G14: #N/A
A15: {=INDEX(Property!A:A, MATCH("Prop Code", Property!A:A, 0) + 1)} -> #N/A | B15: {=_xlfn.LET( _xlpm.primary, IFERROR(INDEX(Property!B:B, MATCH("Fund Code", Property!B:B, 0) + 1), ""), _xlpm.fallback, IFERROR(INDEX(Property!A:A, MATCH("Fund", Property!A:A, 0) + 1), ""), IF( (_xlpm.primary=0)+(_xlpm.primary="")+(_xlpm.primary="NA")+(_xlpm.primary="#N/A"), _xlpm.fallback, _xlpm.primary ) )} | C15: #N/A | E15: #N/A | F15: #N/A | G15: #N/A
... A34: {=INDEX(Property!A:A, MATCH("Prop Code", Property!A:A, 0) + 1)} -> #N/A | B34: {=_xlfn.LET( _xlpm.primary, IFERROR(INDEX(Property!B:B, MATCH("Fund Code", Property!B:B, 0) + 1), ""), _xlpm.fallback, IFERROR(INDEX(Property!A:A, MATCH("Fund", Property!A:A, 0) + 1), ""), IF( (_xlpm.primary=0)+(_xlpm.primary="")+(_xlpm.primary="NA")+(_xlpm.primary="#N/A"), _xlpm.fallback, _xlpm.primary ) )} | C34: #N/A | E34: #N/A | F34: #N/A | G34: #N/A

Sheet PropInt- 10 (LOAD) 
A1: 1. Copy All (Ctrl+A), (Ctrl+C), and Paste Values (Ctrl+Shift+V) 2. No need to Load if iInt is 0 or #N/A | D1: << Delete row before loading
A2: vCode | B2: vIntType | C2: iInt
A3: {=IFERROR( _xlfn._xlws.FILTER(Property!G:I, ISNUMBER(MATCH(Property!H:H, {"Total Units"},0))), _xlfn._xlws.FILTER(Property!I:K, ISNUMBER(MATCH(Property!J:J, {"Total Units"},0))) )} -> #VALUE!

Sheet Loan - 11 (LOAD)
A1: 1. Copy All (Ctrl+A), (Ctrl+C), and Paste Values (Ctrl+Shift+V) 2. In vVendor field, search for the Lender in the Vendor screen and use the Vendor Code instead of the Vendor Name. If the vendor does not exist, create it with the Vendor Type set to “Lender.” 3. If the iAmortTerm field contains “N/A,” leave it blank in the template (do not enter “N/A”) 4. Delete gray rows (rows with no amount) | H1: << Delete row before loading
A2: vCode | B2: vVendor | C2: vLoanType | D2: mOrigLoanAmt | E2: iAmortTerm | F2: vLienPosition | G2: nRate
A3: {=INDEX(Property!G:M, MATCH("Lender", Property!H:H, 0) + _xlfn.SEQUENCE(10), _xlfn.SEQUENCE(1,7))} -> #N/A | B3: #N/A | C3: #N/A | D3: #N/A | E3: #N/A | F3: #N/A | G3: #N/A
A4: #N/A | B4: #N/A | C4: #N/A | D4: #N/A | E4: #N/A | F4: #N/A | G4: #N/A
A5: #N/A | B5: #N/A | C5: #N/A | D5: #N/A | E5: #N/A | F5: #N/A | G5: #N/A
A6: #N/A | B6: #N/A | C6: #N/A | D6: #N/A | E6: #N/A | F6: #N/A | G6: #N/A
A7: #N/A | B7: #N/A | C7: #N/A | D7: #N/A | E7: #N/A | F7: #N/A | G7: #N/A
A8: #N/A | B8: #N/A | C8: #N/A | D8: #N/A | E8: #N/A | F8: #N/A | G8: #N/A
A9: #N/A | B9: #N/A | C9: #N/A | D9: #N/A | E9: #N/A | F9: #N/A | G9: #N/A
A10: #N/A | B10: #N/A | C10: #N/A | D10: #N/A | E10: #N/A | F10: #N/A | G10: #N/A
A11: #N/A | B11: #N/A | C11: #N/A | D11: #N/A | E11: #N/A | F11: #N/A | G11: #N/A
A12: #N/A | B12: #N/A | C12: #N/A | D12: #N/A | E12: #N/A | F12: #N/A | G12: #N/A

Sheet PropParties -12 (LOAD)
A1: 1. Copy All (Ctrl+A), (Ctrl+C), and Paste Values (Ctrl+Shift+V) 2. In vParty field, search for the vendor in the Vendor screen and use the Vendor Code instead of the Vendor Name. If the vendor does not exist, create it using the Vendor Type indicated in the “vType” column of the file 3. Delete gray rows (rows with no vParty) | F1: << Delete row before loading
A2: vCode | B2: vParty | C2: vType | D2: vPreference | E2: dtStart
A3: {=_xlfn._xlws.FILTER( Property!A:D, ISNUMBER(MATCH(Property!C:C,{"Sponsor","Property Manager","General Contractor"},0)))} -> #VALUE! | E3: {=_xlfn.LET( _xlpm.d, IFERROR(INDEX(Property!E:E, MATCH("Start Date", Property!E:E, 0) + 1), ""), _xlpm.c, IFERROR(INDEX(Property!D:D, MATCH("Closing Date", Property!D:D, 0) + 1), ""), IF( OR(_xlpm.d="", _xlpm.d=0, _xlpm.d="NA", ISNA(_xlpm.d), _xlpm.d=DATE(1900,1,0)), IF(OR(_xlpm.c="", _xlpm.c=0, _xlpm.c="NA", ISNA(_xlpm.c), _xlpm.c=DATE(1900,1,0)), TODAY(), _xlpm.c), _xlpm.d ) )} -> 46232
E4: {=_xlfn.LET( _xlpm.d, IFERROR(INDEX(Property!E:E, MATCH("Start Date", Property!E:E, 0) + 1), ""), _xlpm.c, IFERROR(INDEX(Property!D:D, MATCH("Closing Date", Property!D:D, 0) + 1), ""), IF( OR(_xlpm.d="", _xlpm.d=0, _xlpm.d="NA", ISNA(_xlpm.d), _xlpm.d=DATE(1900,1,0)), IF(OR(_xlpm.c="", _xlpm.c=0, _xlpm.c="NA", ISNA(_xlpm.c), _xlpm.c=DATE(1900,1,0)), TODAY(), _xlpm.c), _xlpm.d ) )} -> 46232
E5: {=_xlfn.LET( _xlpm.d, IFERROR(INDEX(Property!E:E, MATCH("Start Date", Property!E:E, 0) + 1), ""), _xlpm.c, IFERROR(INDEX(Property!D:D, MATCH("Closing Date", Property!D:D, 0) + 1), ""), IF( OR(_xlpm.d="", _xlpm.d=0, _xlpm.d="NA", ISNA(_xlpm.d), _xlpm.d=DATE(1900,1,0)), IF(OR(_xlpm.c="", _xlpm.c=0, _xlpm.c="NA", ISNA(_xlpm.c), _xlpm.c=DATE(1900,1,0)), TODAY(), _xlpm.c), _xlpm.d ) )} -> 46232

Sheet Investors - 13 (LOAD)
A1: 1. Copy All (Ctrl+A), (Ctrl+C), and Paste Values (Ctrl+Shift+V) 2. In vInvestor field, search for the Fund Code in the Fund screen (Note: clients sometimes enter the Fund Name instead of the Fund Code). If all lines show 0 or NA, check the following: >TXFinancial_IC table, >Commitment table, >Payment table, and >Case Description for the Fund; If no records are found in any of these, DO NOT LOAD this table 3. For iYear and dtMisc1 fields, if 0 or 1/0/1900, put Close Date; or Date Today if close date is not provided 4. Delete gray rows (rows with no vInvestor) 5. Delete Column C 6. Check Investors screen if duplicate records exist (same vInvestor, vSource, fOwnership), delete the duplicate row here before loading. Note: F3:F9 will populate if this is a Federal Deal; F10:F16 will populate if this is a State Deal | J1: << Delete row before loading
A2: vCode | B2: vInvestor | C2: Legal Entity | D2: iyear | E2: vsource | F2: fOwnership | G2: vResidual | H2: vNotes | I2: dtMisc1
A3: {=INDEX(Property!G:G, MATCH("Fund Code", Property!H:H, 0) + _xlfn.SEQUENCE(7))} -> #N/A | B3: {=C3:C8} -> #N/A | C3: {=IFERROR(INDEX(Property!I:I, MATCH("Legal Entity", Property!I:I, 0) + _xlfn.SEQUENCE(7)),INDEX(Property!H:H, MATCH("Fund Code", Property!H:H, 0) + _xlfn.SEQUENCE(7)))} -> #N/A | D3: {=_xlfn.LET( _xlpm.eff, IFERROR(INDEX(Property!J:J, MATCH("Date", Property!J:J, 0) + _xlfn.SEQUENCE(14)), ""), _xlpm.close, IFERROR(INDEX(Property!D:D, MATCH("Closing Date", Property!D:D, 0) + 1), ""), _xlpm.fallback, IF((_xlpm.close=0)+(_xlpm.close="")+(_xlpm.close="NA")+ISNA(_xlpm.close)+(_xlpm.close=DATE(1900,1,0)), TODAY(), _xlpm.close), IF((_xlpm.eff=0)+(_xlpm.eff="")+(_xlpm.eff="NA")+ISNA(_xlpm.eff)+(_xlpm.eff=DATE(1900,1,0)), _xlpm.fallback + 0*_xlfn.SEQUENCE(14), _xlpm.eff) )} -> 46232 | E3: {=INDEX(Property!K:K, MATCH("Keep As is", Property!K:K, 0) + _xlfn.SEQUENCE(7))} -> #N/A | F3: {=INDEX(Property!L:L, MATCH("Ownership, enter as decimal", Property!L:L, 0) + _xlfn.SEQUENCE(7))} -> #N/A | G3: {=INDEX(Property!M:M, MATCH("State Credit Type", Property!M:M, 0) + _xlfn.SEQUENCE(7))} -> #N/A | H3: {=INDEX(Property!N:N, MATCH("Credit Type", Property!N:N, 0) + _xlfn.SEQUENCE(7))} -> #N/A | I3: {=_xlfn.LET( _xlpm.eff, IFERROR(INDEX(Property!O:O, MATCH("Start Date (same as Date)", Property!O:O, 0) + _xlfn.SEQUENCE(14)), ""), _xlpm.close, IFERROR(INDEX(Property!D:D, MATCH("Closing Date", Property!D:D, 0) + 1), ""), _xlpm.fallback, IF((_xlpm.close=0)+(_xlpm.close="")+(_xlpm.close="NA")+ISNA(_xlpm.close)+(_xlpm.close=DATE(1900,1,0)), TODAY(), _xlpm.close), IF((_xlpm.eff=0)+(_xlpm.eff="")+(_xlpm.eff="NA")+ISNA(_xlpm.eff)+(_xlpm.eff=DATE(1900,1,0)), _xlpm.fallback + 0*_xlfn.SEQUENCE(14), _xlpm.eff) )} -> 46232
A4: #N/A | B4: #N/A | C4: #N/A | D4: 46232 | E4: #N/A | F4: #N/A | G4: #N/A | H4: #N/A | I4: 46232
A5: #N/A | B5: #N/A | C5: #N/A | D5: 46232 | E5: #N/A | F5: #N/A | G5: #N/A | H5: #N/A | I5: 46232
A6: #N/A | B6: #N/A | C6: #N/A | D6: 46232 | E6: #N/A | F6: #N/A | G6: #N/A | H6: #N/A | I6: 46232
A7: #N/A | B7: #N/A | C7: #N/A | D7: 46232 | E7: #N/A | F7: #N/A | G7: #N/A | H7: #N/A | I7: 46232
A8: #N/A | B8: #N/A | C8: #N/A | D8: 46232 | E8: #N/A | F8: #N/A | G8: #N/A | H8: #N/A | I8: 46232
A9: #N/A | B9: =_xlfn.XLOOKUP(E9,Property!K29,Property!H29) -> #N/A | C9: #N/A | D9: 46232 | E9: #N/A | F9: #N/A | G9: #N/A | H9: #N/A | I9: 46232
A10: {=IF(AND(NOT(ISNA(B10)),B10<>"N/A",B10<>"NA",B10<>0,B10<>""),INDEX(Property!A:A,MATCH("Prop Code",Property!A:A,0)+1),"")} -> #N/A | B10: {=IFERROR(INDEX(Property!E:E, MATCH("Legal Entities", Property!E:E, 0) + _xlfn.SEQUENCE(6)),INDEX(Property!F:F, MATCH("Legal Entities", Property!F:F, 0) + _xlfn.SEQUENCE(6)))} -> #N/A | D10: 46232 | E10: Legal Entity | F10: {=IFERROR(INDEX(Property!F:F, MATCH("Original Commitment", Property!F:F, 0) + _xlfn.SEQUENCE(6)) / SUM(INDEX(Property!F:F, MATCH("Original Commitment", Property!F:F, 0) + _xlfn.SEQUENCE(6))),INDEX(Property!G:G, MATCH("Original Commitment", Property!G:G, 0) + _xlfn.SEQUENCE(6)) / SUM(INDEX(Property!G:G, MATCH("Original Commitment", Property!G:G, 0) + _xlfn.SEQUENCE(6))))} -> #N/A | H10: State | I10: 46232
A11: {=IF(AND(NOT(ISNA(B11)),B11<>"N/A",B11<>"NA",B11<>0,B11<>""),INDEX(Property!A:A,MATCH("Prop Code",Property!A:A,0)+1),"")} -> #N/A | B11: #N/A | D11: 46232 | E11: Legal Entity | F11: #N/A | H11: State | I11: 46232
A12: {=IF(AND(NOT(ISNA(B12)),B12<>"N/A",B12<>"NA",B12<>0,B12<>""),INDEX(Property!A:A,MATCH("Prop Code",Property!A:A,0)+1),"")} -> #N/A | B12: #N/A | D12: 46232 | E12: Legal Entity | F12: #N/A | H12: State | I12: 46232
A13: {=IF(AND(NOT(ISNA(B13)),B13<>"N/A",B13<>"NA",B13<>0,B13<>""),INDEX(Property!A:A,MATCH("Prop Code",Property!A:A,0)+1),"")} -> #N/A | B13: #N/A | D13: 46232 | E13: Legal Entity | F13: #N/A | H13: State | I13: 46232
A14: {=IF(AND(NOT(ISNA(B14)),B14<>"N/A",B14<>"NA",B14<>0,B14<>""),INDEX(Property!A:A,MATCH("Prop Code",Property!A:A,0)+1),"")} -> #N/A | B14: #N/A | D14: 46232 | E14: Legal Entity | F14: #N/A | H14: State | I14: 46232
A15: {=IF(AND(NOT(ISNA(B15)),B15<>"N/A",B15<>"NA",B15<>0,B15<>""),INDEX(Property!A:A,MATCH("Prop Code",Property!A:A,0)+1),"")} -> #N/A | B15: #N/A | D15: 46232 | E15: Legal Entity | F15: #N/A | H15: State | I15: 46232
A16: {=IF(AND(NOT(ISNA(B16)),B16<>"N/A",B16<>"NA",B16<>0,B16<>""),INDEX(Property!A:A,MATCH("Prop Code",Property!A:A,0)+1),"")} -> #N/A | B16: {=INDEX(Property!A:A, MATCH("Fund", Property!A:A, 0) + 1)} -> #N/A | D16: 46232 | E16: Manual | F16: 1 | H16: NULL | I16: 46232
