Workbook

Sheet GENERAL Instructions
A1: Identify the Type of Setup Requested by the NW Client

Sheet Fund Setup Instructions
A1: Fund Setup:
A2: A. Create Fund Code | B2: Nationwide should provide requested code, if available use this code. If not, create a code that is not being used in system, try to follow naming convention of similar funds. Remember to only use lowercase letters. (If unsure, reach out to client in the case. See screenshot.)
A3: CREATE FUND CODE HERE: | B3: sample1
A4: D. List all missing items | B4: • Review all tables for #N/A or NULL values (highlighted in yellow). • Document all missing items before deleting any rows or columns and proceeding with loading the tabs. • After the setup is completed, refer to Section F to input the required values.
A5: E. Process Tabs | B5: • Follow instructions in each tab (they will auto-populate after you followed the General Instructions) • Batch LOAD and manually enter Collection Rules • After successful load, return to this page for validation
A6: F. Fund & Investment Verification Checklist | B6: MRI Screen | C6: Field | D6: Required Value | E6: Impact if Incorrect | F6: Verified
B7: Fund Screen | C7: Fund Type | D7: • If it is not provided in the file, reach out to the client to request the missing fund type. • Advise the client of any potential impact or issues that may arise if the information remains incomplete. | E7: Incomplete Setup; Wouldn't be able to identify Billing Type, hence, no Collection Rules could be setup | F7: FALSE
B8: Fund Screen | C8: Billing Type | D8: • vAMFeesDescription; some types are not reflected on screen when batchloaded, need to double-check and manually enter. | E8: Incomplete Setup | F8: FALSE
B9: Fund Screen-Third Party Relationships | C9: Relationship/Link Type (Fund Manager) | D9: •If it is not provided in the file, reach out to the client to request the missing Fund Manager. •Once received, proceed with adding the relationship. | E9: Incomplete Setup | F9: FALSE
B10: Fund Screen | C10: Withhold from Export | D10: Check the box. Please note that once it has been checked, it should not be unchecked or modified. | E10: Once the fund is reviewed by NW, they'll remove that hold so it could flow through their process. Updating that box again, will cause issues. It is going to send that fund through their process again. | F10: FALSE
A11: G. Post-verification Step (Checklist completed) | B11: FOR FUND ONLY: • Email client setup has been completed If the client reports that the Fund is not appearing in the Entity List Report, this typically indicates that no property has been associated with the Fund and Legal Entity on the Investor screen. If this is a Fund Setup case only, please advise the client accordingly. | C11: FOR PROPETY AND FUND: • Proceed to Property Setup and use the setup Fund here for the fields requiring Fund Codes

Sheet Fund

Sheet Upper Tier Fund

Sheet Fund - 5 (LOAD)
A1: 1. Copy All (Ctrl+A), (Ctrl+C), and Paste Values (Ctrl+Shift+V) 2. vTransType will auto-populate if a Fund Type is provided in the file. If NOT, select the appropriate option from the dropdown based on the Tax Credit Type (column E) IF Tax Credit Type = i. State Certificated > Certificated ii. State Historic > Historic Proprietary Fund iii. Federal Solar > Energy Proprietary Fund iv. Federal LIHTC > LIHTC Proprietary Fund v. State Certificated > Certificated vi. If unsure of what billing type should be, query fund table to find similar deal and mimic billing type or ask NW Note: Solar Proprietary Fund should be Energy Proprietary Fund 3. For vAMFeesDescription field, also refer to Tax Credit Type in column E. (Choose in the dropdown) IF Tax Credit Type = i. Federal LIHTC Multi Investor Fund or Historic Multi, or Solar multi > Multi Investor Fund ii. Federal LIHTC Proprietary or Historic Proprietary, or Solar/Energy Proprietary > Proprietary Fund iii. State Proprietary/State Historic/State Long Term/State Direct > State Long Term Fund iv. Certificated Fund, Guaranteed Fund or Middle Tier Guaranteed Fund/Debt > Other Fund v. If unsure of what billing type should be, query fund table to find similar deal and mimic billing type or ask NW 4. iPipeline is always '1' 5. Delete Gray Columns 6. Delete Column E Note: Certificated Fund Types do not have a Tax ID (vPartnershipTaxID) and Expiration Date (dtClosed) | I1: << Delete row before loading
A2: vCode | B2: vPartnershipTaxID | C2: vPartnershipName | D2: dtClosed | E2: Tax Credit Type | F2: vTransType | G2: vAMFeesDescription | H2: iPipeline
A3: ='Fund Setup Instructions'!B3 -> sample1 | B3: {=SUBSTITUTE(SUBSTITUTE(TRIM(INDEX(Fund!M:M, MATCH("Tax ID", Fund!M:M, 0)+1)),"-","")," ","")} -> #N/A | C3: {=IFERROR(INDEX(Fund!A:A,MATCH("Deal Name ",Fund!A:A,0)+1),IFERROR(INDEX(Fund!A:A,MATCH("Fund Name ",Fund!A:A,0)+1),INDEX('Upper Tier Fund'!A:A,MATCH("Fund",'Upper Tier Fund'!A:A,0)+1)))} -> #N/A | D3: {=INDEX(Fund!O:O, MATCH("Expiration Date",Fund!O:O, 0)+1)} -> #N/A | E3: {=IFERROR(INDEX(Fund!B:B, MATCH("Tax Credit Type ",Fund!B:B, 0)+1),INDEX('Upper Tier Fund'!C:C, MATCH("Fund Type",'Upper Tier Fund'!C:C, 0)+1))} -> #N/A | F3: {=IFERROR(INDEX(Fund!P:P, MATCH("Fund Type", Fund!P:P, 0)+1), "")} | G3: Proprietary Fund | H3: 1

Sheet PropParties -6 (LOAD)
A1: 1. Copy All (Ctrl+A), (Ctrl+C), and Paste Values (Ctrl+Shift+V) 2. For vParty, search for the vendor in the Vendor screen and use the Vendor Code instead of the Vendor Name. If the vendor does not exist, create it using the Vendor Type indicated in the “vType” column of the file 3. Delete Gray Rows | F1: << Delete row before loading
A2: vCode | B2: vParty | C2: vType | D2: vPreference | E2: dtStart
A3: ='Fund Setup Instructions'!B$3 -> sample1 | B3: {=IFERROR(INDEX(Fund!N:N, MATCH("Fund Manager",Fund!N:N, 0)+1),INDEX('Upper Tier Fund'!B:B, MATCH("Fund Manager",'Upper Tier Fund'!B:B, 0)+1))} -> #N/A | C3: Fund Manager | D3: 1 | E3: {=IFERROR(INDEX(Fund!D:D,MATCH("Closing Date ",Fund!D:D,0)+1),INDEX('Upper Tier Fund'!D:D,MATCH("Closing Date",'Upper Tier Fund'!D:D,0)+1))} -> #N/A
A4: ='Fund Setup Instructions'!B$3 -> sample1 | B4: {=INDEX(Fund!I:I, MATCH("General Partner ",Fund!I:I, 0)+1)} -> #N/A | C4: General Partner | D4: 1 | E4: {=INDEX(Fund!E:E,MATCH("Amort Start Date",Fund!E:E,0)+1)} -> #N/A

Sheet Owner - 7 (LOAD)
A1: 1. Copy All (Ctrl+A), (Ctrl+C), and Paste Values (Ctrl+Shift+V) 2. vType is always 'Limited Partner' 3. Double-check if the address is formatted correctly City – Sometimes incorrectly included in the State field State – Must be a two-letter abbreviation ZIP Code – In US, a standard ZIP Code is always 5 digits. If only 4 digits are provided, add a zero in front 4. bFund is always 'booltrue' 5. Delete Gray Columns Note: Certificated Fund Types do not have a Tax ID (vTaxID) | K1: << Delete row before loading
A2: vCode | B2: vTaxID | C2: vName | D2: vType | E2: vCity | F2: vState | G2: vZip | H2: vTarget | I2: vMisc3 | J2: bFund
A3: ='Fund Setup Instructions'!B$3 -> sample1 | B3: {=SUBSTITUTE(SUBSTITUTE(TRIM(INDEX(Fund!M:M, MATCH("Tax ID", Fund!M:M, 0)+1)),"-","")," ","")} -> #N/A | C3: {=IFERROR(INDEX(Fund!A:A,MATCH("Deal Name ",Fund!A:A,0)+1),IFERROR(INDEX(Fund!A:A,MATCH("Fund Name ",Fund!A:A,0)+1),INDEX('Upper Tier Fund'!A:A,MATCH("Fund",'Upper Tier Fund'!A:A,0)+1)))} -> #N/A | D3: Limited Partner | E3: {=INDEX(Fund!F:F, MATCH("Partnership City ",Fund!F:F, 0)+1)} -> #N/A | F3: {=INDEX(Fund!G:G, MATCH("Partnership State ",Fund!G:G, 0)+1)} -> #N/A | G3: {=INDEX(Fund!H:H, MATCH("Postal Code ",Fund!H:H, 0)+1)} -> #N/A | H3: {=IFERROR(INDEX(Fund!B:B, MATCH("Tax Credit Type ",Fund!B:B, 0)+1),INDEX('Upper Tier Fund'!C:C,MATCH("Fund Type",'Upper Tier Fund'!C:C,0)+1))} -> #N/A | I3: {=INDEX(Fund!C:C, MATCH("Real Estate Type ",Fund!C:C, 0)+1)} -> #N/A | J3: booltrue

Sheet Investors - 8 (LOAD)
A1: 1. Copy All (Ctrl+A), (Ctrl+C), and Paste Values (Ctrl+Shift+V) 2. For vInvestor, search for the Fund Code in the Fund screen (Note: clients sometimes enter the Fund Name instead of the Fund Code). If no record is found, ask client how to proceed. DO NOT ADD FUND. 3. Format fOwnership and fPriorityReturn in decimals (eg. If in excel sheet it shows 99.99%, it should be 0.9999) 4. vCodeEntityType and vInvestorEntityType are always 'Owner' 5. Delete Gray Rows | I1: << Delete row before loading
A2: vCode | B2: vInvestor | C2: iyear | D2: vsource | E2: fOwnership | F2: fPriorityReturn | G2: vCodeEntityType | H2: vInvestorEntityType
A3: ='Fund Setup Instructions'!B$3 -> sample1 | B3: {=IFERROR(INDEX(Fund!J:J,MATCH("Legal Entity/Account ",Fund!J:J,0)+_xlfn.SEQUENCE(7)),IFERROR(INDEX('Upper Tier Fund'!F:F,MATCH("Legal Entities",'Upper Tier Fund'!F:F,0)+_xlfn.SEQUENCE(7)),INDEX('Upper Tier Fund'!E:E,MATCH("Legal Entities",'Upper Tier Fund'!E:E,0)+_xlfn.SEQUENCE(7))))} -> #N/A | C3: {=IFERROR(INDEX(Fund!D:D,MATCH("Closing Date ",Fund!D:D,0)+1),INDEX('Upper Tier Fund'!D:D,MATCH("Closing Date",'Upper Tier Fund'!D:D,0)+1))} -> #N/A | D3: Legal Entity | E3: {=IFERROR(INDEX(Fund!K:K,MATCH("Commitment ",Fund!K:K,0)+_xlfn.SEQUENCE(7))/ SUM(INDEX(Fund!K:K,MATCH("Commitment ",Fund!K:K,0)+_xlfn.SEQUENCE(7))),IFERROR(INDEX('Upper Tier Fund'!G:G,MATCH("Original Commitment",'Upper Tier Fund'!G:G,0)+_xlfn.SEQUENCE(7))/ SUM(INDEX('Upper Tier Fund'!G:G,MATCH("Original Commitment",'Upper Tier Fund'!G:G,0)+_xlfn.SEQUENCE(7))),INDEX('Upper Tier Fund'!F:F,MATCH("Original Commitment",'Upper Tier Fund'!F:F,0)+_xlfn.SEQUENCE(7))/ SUM(INDEX('Upper Tier Fund'!F:F,MATCH("Original Commitment",'Upper Tier Fund'!F:F,0)+_xlfn.SEQUENCE(7)))))} -> #N/A | F3: {=IFERROR(INDEX(Fund!L:L,MATCH("Ownership ",Fund!L:L,0)+_xlfn.SEQUENCE(7)),"")} | G3: Owner | H3: Owner
A4: ='Fund Setup Instructions'!B$3 -> sample1 | B4: #N/A | C4: {=IFERROR(INDEX(Fund!D:D,MATCH("Closing Date ",Fund!D:D,0)+1),INDEX('Upper Tier Fund'!D:D,MATCH("Closing Date",'Upper Tier Fund'!D:D,0)+1))} -> #N/A | D4: Legal Entity | E4: #N/A | G4: Owner | H4: Owner
A5: ='Fund Setup Instructions'!B$3 -> sample1 | B5: #N/A | C5: {=IFERROR(INDEX(Fund!D:D,MATCH("Closing Date ",Fund!D:D,0)+1),INDEX('Upper Tier Fund'!D:D,MATCH("Closing Date",'Upper Tier Fund'!D:D,0)+1))} -> #N/A | D5: Legal Entity | E5: #N/A | G5: Owner | H5: Owner
A6: ='Fund Setup Instructions'!B$3 -> sample1 | B6: #N/A | C6: {=IFERROR(INDEX(Fund!D:D,MATCH("Closing Date ",Fund!D:D,0)+1),INDEX('Upper Tier Fund'!D:D,MATCH("Closing Date",'Upper Tier Fund'!D:D,0)+1))} -> #N/A | D6: Legal Entity | E6: #N/A | G6: Owner | H6: Owner
A7: ='Fund Setup Instructions'!B$3 -> sample1 | B7: #N/A | C7: {=IFERROR(INDEX(Fund!D:D,MATCH("Closing Date ",Fund!D:D,0)+1),INDEX('Upper Tier Fund'!D:D,MATCH("Closing Date",'Upper Tier Fund'!D:D,0)+1))} -> #N/A | D7: Legal Entity | E7: #N/A | G7: Owner | H7: Owner
A8: ='Fund Setup Instructions'!B$3 -> sample1 | B8: #N/A | C8: {=IFERROR(INDEX(Fund!D:D,MATCH("Closing Date ",Fund!D:D,0)+1),INDEX('Upper Tier Fund'!D:D,MATCH("Closing Date",'Upper Tier Fund'!D:D,0)+1))} -> #N/A | D8: Legal Entity | E8: #N/A | G8: Owner | H8: Owner
A9: ='Fund Setup Instructions'!B$3 -> sample1 | B9: #N/A | C9: {=IFERROR(INDEX(Fund!D:D,MATCH("Closing Date ",Fund!D:D,0)+1),INDEX('Upper Tier Fund'!D:D,MATCH("Closing Date",'Upper Tier Fund'!D:D,0)+1))} -> #N/A | D9: Legal Entity | E9: #N/A | G9: Owner | H9: Owner

Sheet TXFinancial_IC - 9 (LOAD)
A1: 1. Copy All (Ctrl+A), (Ctrl+C), and Paste Values (Ctrl+Shift+V) 2. vTransType is always 'Orig Commit' | E1: << Delete row before loading
A2: vCode | B2: vTransType | C2: mAmount | D2: dtEffective
A3: ='Fund Setup Instructions'!B$3 -> sample1 | B3: Orig Commit | C3: {=IFERROR( SUM(INDEX(Fund!K:K,MATCH("Commitment ",Fund!K:K,0)+_xlfn.SEQUENCE(7))), IFERROR( SUM(INDEX('Upper Tier Fund'!G:G,MATCH("Original Commitment",'Upper Tier Fund'!G:G,0)+_xlfn.SEQUENCE(7))), SUM(INDEX('Upper Tier Fund'!F:F,MATCH("Original Commitment",'Upper Tier Fund'!F:F,0)+_xlfn.SEQUENCE(7)))))} -> #N/A | D3: {=IFERROR(INDEX(Fund!D:D,MATCH("Closing Date ",Fund!D:D,0)+1),INDEX('Upper Tier Fund'!D:D,MATCH("Closing Date",'Upper Tier Fund'!D:D,0)+1))} -> #N/A

Sheet Data Validation
A1: Billing Type (fund.vAMFeesDescription) | C1: Date Type (event_dates.vDateType) | E1: Fund Type (fund.vTransType) | F1: K21:K53 | H1: select * from Collection_Rule where vCode = 'your vCode'
A2: Disposed | C2: Actual | E2: Certificated | F2: 8 | H2: UID | I2: iType_ID
A3: Multi-Investor fund | C3: Projected | E3: Disposed | F3: 7
A4: Omit | E4: Guaranteed Fund | F4: 5
A5: Other Fund | E5: Historic Multi-Investor Fund | F5: 2
A6: Proprietary fund | E6: Historic Proprietary Fund | F6: 2
A7: State Long-Term Fund | E7: LIHTC Multi-Investor Fund | F7: 3
E8: LIHTC Proprietary Fund | F8: 3
E9: Middle Tier Guaranteed | F9: 6
E10: New Market Fund | F10: 6
E11: Other | F11: 7
E12: State Historic | F12: 2
E13: State Immediate Fund | F13: 4
E14: State Long-Term Fund | F14: 4
E15: State Other | F15: 4
E16: State Proprietary Fund | F16: 4
E17: Energy Multi-Investor Fund | F17: 1
E18: Energy Proprietary Fund | F18: 1
A20: vCode | C20: iType_ID | D20: dtStart | E20: dtEnd | F20: vFrequency | G20: vCurrentPeriod | H20: dtCurrentDue | I20: bAuto | J20: dtActualDue | K20: F2:F18
A21: medbess | B21: Interims | C21: 2 | D21: {=IFERROR(INDEX(Fund!D:D,MATCH("Closing Date ",Fund!D:D,0)+1),INDEX('Upper Tier Fund'!D:D,MATCH("Closing Date",'Upper Tier Fund'!D:D,0)+1))} -> #N/A | E21: NULL | F21: Quarterly | G21: 46203 | H21: 46249 | I21: boolfalse | J21: 46157 | K21: 1
A22: medbess | B22: Audits | C22: 4 | D22: {=IFERROR(INDEX(Fund!D:D,MATCH("Closing Date ",Fund!D:D,0)+1),INDEX('Upper Tier Fund'!D:D,MATCH("Closing Date",'Upper Tier Fund'!D:D,0)+1))} -> #N/A | E22: NULL | F22: Annually | G22: 46387 | H22: 46461 | I22: boolfalse | J22: 46461 | K22: 1
A23: medbess | B23: K1 | C23: 17 | D23: {=IFERROR(INDEX(Fund!D:D,MATCH("Closing Date ",Fund!D:D,0)+1),INDEX('Upper Tier Fund'!D:D,MATCH("Closing Date",'Upper Tier Fund'!D:D,0)+1))} -> #N/A | E23: NULL | F23: Annually | G23: 46387 | H23: 46461 | I23: boolfalse | J23: 46461 | K23: 1
A24: medbess | B24: Investor Report | C24: 33 | D24: {=IFERROR(INDEX(Fund!D:D,MATCH("Closing Date ",Fund!D:D,0)+1),INDEX('Upper Tier Fund'!D:D,MATCH("Closing Date",'Upper Tier Fund'!D:D,0)+1))} -> #N/A | E24: NULL | F24: Quarterly | G24: 46203 | H24: 46249 | I24: boolfalse | J24: 46157 | K24: 1
A25: medbess | B25: AHIC - Quarter | C25: 36 | D25: {=IFERROR(INDEX(Fund!D:D,MATCH("Closing Date ",Fund!D:D,0)+1),INDEX('Upper Tier Fund'!D:D,MATCH("Closing Date",'Upper Tier Fund'!D:D,0)+1))} -> #N/A | E25: NULL | F25: Quarterly | G25: 46203 | H25: 46249 | I25: boolfalse | J25: 46157 | K25: 1
A26: medbess | B26: Benefit Schedule | C26: 38 | D26: {=IFERROR(INDEX(Fund!D:D,MATCH("Closing Date ",Fund!D:D,0)+1),INDEX('Upper Tier Fund'!D:D,MATCH("Closing Date",'Upper Tier Fund'!D:D,0)+1))} -> #N/A | E26: NULL | F26: Annually | G26: 46295 | H26: 46341 | I26: boolfalse | J26: 46341 | K26: 1
A27: medbess | B27: Property Summary | C27: 44 | D27: {=IFERROR(INDEX(Fund!D:D,MATCH("Closing Date ",Fund!D:D,0)+1),INDEX('Upper Tier Fund'!D:D,MATCH("Closing Date",'Upper Tier Fund'!D:D,0)+1))} -> #N/A | E27: NULL | F27: Quarterly | G27: 46203 | H27: 46249 | I27: boolfalse | J27: 46157 | K27: 1
A28: medbess | B28: GAAP Losses/Credits | C28: 53 | D28: {=IFERROR(INDEX(Fund!D:D,MATCH("Closing Date ",Fund!D:D,0)+1),INDEX('Upper Tier Fund'!D:D,MATCH("Closing Date",'Upper Tier Fund'!D:D,0)+1))} -> #N/A | E28: NULL | F28: Quarterly | G28: 46203 | H28: 46249 | I28: boolfalse | J28: 46157 | K28: 1
A29: acmultiz | B29: Audits | C29: 4 | D29: {=IFERROR(INDEX(Fund!D:D,MATCH("Closing Date ",Fund!D:D,0)+1),INDEX('Upper Tier Fund'!D:D,MATCH("Closing Date",'Upper Tier Fund'!D:D,0)+1))} -> #N/A | E29: NULL | F29: Annually | G29: 46387 | H29: 46461 | I29: boolfalse | J29: 46461 | K29: 2
A30: acmultiz | B30: K1 | C30: 17 | D30: {=IFERROR(INDEX(Fund!D:D,MATCH("Closing Date ",Fund!D:D,0)+1),INDEX('Upper Tier Fund'!D:D,MATCH("Closing Date",'Upper Tier Fund'!D:D,0)+1))} -> #N/A | E30: NULL | F30: Annually | G30: 46387 | H30: 46461 | I30: boolfalse | J30: 46461 | K30: 2
A31: ohio5 | B31: Interims | C31: 2 | D31: {=IFERROR(INDEX(Fund!D:D,MATCH("Closing Date ",Fund!D:D,0)+1),INDEX('Upper Tier Fund'!D:D,MATCH("Closing Date",'Upper Tier Fund'!D:D,0)+1))} -> #N/A | E31: NULL | F31: Quarterly | G31: 46203 | H31: 46249 | I31: boolfalse | J31: 46157 | K31: 3
A32: ohio5 | B32: Audits | C32: 4 | D32: {=IFERROR(INDEX(Fund!D:D,MATCH("Closing Date ",Fund!D:D,0)+1),INDEX('Upper Tier Fund'!D:D,MATCH("Closing Date",'Upper Tier Fund'!D:D,0)+1))} -> #N/A | E32: NULL | F32: Annually | G32: 46387 | H32: 46461 | I32: boolfalse | J32: 46461 | K32: 3
... A53: nefbf1 | B53: K1 | C53: 17 | D53: {=IFERROR(INDEX(Fund!D:D,MATCH("Closing Date ",Fund!D:D,0)+1),INDEX('Upper Tier Fund'!D:D,MATCH("Closing Date",'Upper Tier Fund'!D:D,0)+1))} -> #N/A | E53: NULL | F53: Annually | G53: 46387 | H53: 46461 | I53: boolfalse | J53: 46461 | K53: 7

Sheet Event_Dates - 10 (LOAD)
A1: 1. Copy All (Ctrl+A), (Ctrl+C), and Paste Values (Ctrl+Shift+V) 2. For vDateType: • Acquisition= 'Actual' • Lease Up (Choose in the dropdown) • Federal Deals= 'Actual' • State Deals= 'Projected' • Other Deals= 'Actual' If not sure, confirm with client in the case 3. Delete Gray Rows Note: Certificated Fund Types do not have Qualified Occupancy Event | G1: << Delete row before loading
A2: vCode | B2: vEventType | C2: vEvent | D2: vDateType | E2: dtEvent | F2: dtEntry
A3: ='Fund Setup Instructions'!B$3 -> sample1 | B3: Acquisition | C3: Closing | D3: Actual | E3: {=IFERROR(INDEX(Fund!D:D,MATCH("Closing Date ",Fund!D:D,0)+1),INDEX('Upper Tier Fund'!D:D,MATCH("Closing Date",'Upper Tier Fund'!D:D,0)+1))} -> #N/A | F3: =TODAY() -> 46232
A4: ='Fund Setup Instructions'!B$3 -> sample1 | B4: Lease Up | C4: Qualified Occupancy | D4: Actual | E4: {=INDEX(Fund!E:E,MATCH("Amort Start Date",Fund!E:E,0)+1)} -> #N/A | F4: =TODAY() -> 46232

Sheet Collection Rules
A1: MANUAL ENTRY OR BATCHLOAD sheet 12 and 13:
A2: Manual entry:
A3: Collection Rules
A4: Go to collection rules screen and set up rules as follows based on Fund Type. Required rules are on the table below:
A5: Easiest way is to select a Fund which is similar (same Fund Type) and clone the records for the new fund.
A6: **Either look manually on the Fund screen for funds with similar fund type or search in query.
A7: **Only modify Start Date when Cloning; DO NOT remove notifications but DELETE the emails/contacts in the notifications.
A8: Start Date= Closing Date
A9: Fund Type | B9: Collection Rules | C9: Fund to Clone
A10: Solar or Energy Multi/Proprietary | B10: Audits, k1s, Benefit schedules, Investor Reports, Ahic, Interim Financials, Property Summary, GAAP Loses/Credits | C10: medbess
A11: Historic Multi/Historic Proprietary | B11: Audits, k1s | C11: acmultiz, wohi113h
A12: LIHTC Multi/LIHTC Proprietary | B12: Audits, k1s, Benefit schedules, Investor Reports, Ahic, Interim Financials, Property Summar,GAAP Loses/Credits | C12: ohio5, usa153
A13: State Proprietary Fund/State Long Term | B13: Audits, k1s | C13: modtob
A14: Guaranteed Fund | B14: Audits, k1s | C14: discahif
A15: Middle Tier | B15: Audits, k1s | C15: **Need to verify from client, because funds with similar type has 8 collection rules like usa150 and pnc83
A16: Other | B16: Interim Financials, Audits, k1s | C16: nefbf1
A17: Certificated | B17: No Collection Rules Needed, No Expiration Date needed, no Tax ID needed | C17: wohi113

Sheet Collection_Rule - 12 (LOAD)
A1: 1. Choose the Fund Type from the Drop Down in cell A3 (refer to vTransType in the Fund table) 2. Copy All (Ctrl+A), (Ctrl+C), and Paste Values (Ctrl+Shift+V) 3. Delete Column A 4. Delete Gray Rows Note: Certificated Fund Types do not have Collection Rules | K1: << Delete row before loading
A2: Fund Type (vTranstype) | B2: vCode | C2: iType_ID | D2: dtStart | E2: dtEnd | F2: vFrequency | G2: vCurrentPeriod | H2: dtCurrentDue | I2: bAuto | J2: dtActualDue
A3: Energy Proprietary Fund | B3: ='Fund Setup Instructions'!B$3 -> sample1 | C3: {=_xlfn._xlws.FILTER('Data Validation'!C21:J53,'Data Validation'!K21:K53=_xlfn.XLOOKUP(A3,'Data Validation'!E2:E18,'Data Validation'!F2:F18),"No Collection Rules")} -> 2 | D3: #N/A | E3: NULL | F3: Quarterly | G3: 46203 | H3: 46249 | I3: boolfalse | J3: 46157
B4: ='Fund Setup Instructions'!B$3 -> sample1 | C4: 4 | D4: #N/A | E4: NULL | F4: Annually | G4: 46387 | H4: 46461 | I4: boolfalse | J4: 46461
B5: ='Fund Setup Instructions'!B$3 -> sample1 | C5: 17 | D5: #N/A | E5: NULL | F5: Annually | G5: 46387 | H5: 46461 | I5: boolfalse | J5: 46461
B6: ='Fund Setup Instructions'!B$3 -> sample1 | C6: 33 | D6: #N/A | E6: NULL | F6: Quarterly | G6: 46203 | H6: 46249 | I6: boolfalse | J6: 46157
B7: ='Fund Setup Instructions'!B$3 -> sample1 | C7: 36 | D7: #N/A | E7: NULL | F7: Quarterly | G7: 46203 | H7: 46249 | I7: boolfalse | J7: 46157
B8: ='Fund Setup Instructions'!B$3 -> sample1 | C8: 38 | D8: #N/A | E8: NULL | F8: Annually | G8: 46295 | H8: 46341 | I8: boolfalse | J8: 46341
B9: ='Fund Setup Instructions'!B$3 -> sample1 | C9: 44 | D9: #N/A | E9: NULL | F9: Quarterly | G9: 46203 | H9: 46249 | I9: boolfalse | J9: 46157
B10: ='Fund Setup Instructions'!B$3 -> sample1 | C10: 53 | D10: #N/A | E10: NULL | F10: Quarterly | G10: 46203 | H10: 46249 | I10: boolfalse | J10: 46157

Sheet Notification_Rule - 13 (LOAD)
A1: 1. Follow instructions written on the Green Box below. Open SQL. 2. Copy All (Ctrl+A), (Ctrl+C), and Paste Values (Ctrl+Shift+V) 3. Delete Gray Rows 4. Delete Column A and B before loading. Note: Collection_Rule in sheet 12 must be loaded first | I1: << Delete row before loading
A2: iTypeID | B2: Data Type | C2: iCollRuleID | D2: vType | E2: iLag | F2: iEmailID | G2: bActive | H2: vNotes
A3: 2 | B3: Interims | C3: =_xlfn.XLOOKUP(A3,'Data Validation'!$I$3:$I$10,'Data Validation'!$H$3:$H$10) -> #N/A | D3: Email | E3: 0 | F3: 2 | G3: BOOLTRUE | H3: NULL
A4: 2 | B4: Interims | C4: =_xlfn.XLOOKUP(A4,'Data Validation'!$I$3:$I$10,'Data Validation'!$H$3:$H$10) -> #N/A | D4: Email | E4: 45 | F4: 6 | G4: BOOLTRUE | H4: NULL
A5: 4 | B5: Audits | C5: =_xlfn.XLOOKUP(A5,'Data Validation'!$I$3:$I$10,'Data Validation'!$H$3:$H$10) -> #N/A | D5: Email | E5: 0 | F5: 11 | G5: BOOLTRUE | H5: NULL
A6: 4 | B6: Audits | C6: =_xlfn.XLOOKUP(A6,'Data Validation'!$I$3:$I$10,'Data Validation'!$H$3:$H$10) -> #N/A | D6: Email | E6: 45 | F6: 12 | G6: BOOLTRUE | H6: NULL
A7: 17 | B7: K1 | C7: =_xlfn.XLOOKUP(A7,'Data Validation'!$I$3:$I$10,'Data Validation'!$H$3:$H$10) -> #N/A | D7: Email | E7: 0 | F7: 10 | G7: BOOLTRUE | H7: NULL
A8: 17 | B8: K1 | C8: =_xlfn.XLOOKUP(A8,'Data Validation'!$I$3:$I$10,'Data Validation'!$H$3:$H$10) -> #N/A | D8: Email | E8: 45 | F8: 13 | G8: BOOLTRUE | H8: NULL
A9: 36 | B9: AHIC - Quarter | C9: =_xlfn.XLOOKUP(A9,'Data Validation'!$I$3:$I$10,'Data Validation'!$H$3:$H$10) -> #N/A | D9: Email | E9: 0 | F9: 5 | G9: BOOLTRUE | H9: NULL
A10: 36 | B10: AHIC - Quarter | C10: =_xlfn.XLOOKUP(A10,'Data Validation'!$I$3:$I$10,'Data Validation'!$H$3:$H$10) -> #N/A | D10: Email | E10: 45 | F10: 9 | G10: BOOLTRUE | H10: NULL
A11: 38 | B11: Benefit Schedule | C11: =_xlfn.XLOOKUP(A11,'Data Validation'!$I$3:$I$10,'Data Validation'!$H$3:$H$10) -> #N/A | D11: Email | E11: 0 | F11: 3 | G11: BOOLTRUE | H11: NULL
A12: 38 | B12: Benefit Schedule | C12: =_xlfn.XLOOKUP(A12,'Data Validation'!$I$3:$I$10,'Data Validation'!$H$3:$H$10) -> #N/A | D12: Email | E12: 45 | F12: 7 | G12: BOOLTRUE | H12: NULL
A13: 53 | B13: GAAP Losses/Credits | C13: =_xlfn.XLOOKUP(A13,'Data Validation'!$I$3:$I$10,'Data Validation'!$H$3:$H$10) -> #N/A | D13: Email | E13: 0 | F13: 4 | G13: BOOLTRUE | H13: NULL
A14: 53 | B14: GAAP Losses/Credits | C14: =_xlfn.XLOOKUP(A14,'Data Validation'!$I$3:$I$10,'Data Validation'!$H$3:$H$10) -> #N/A | D14: Email | E14: 45 | F14: 8 | G14: BOOLTRUE | H14: NULL
